debis/__init__.py
debis/person.py
debis/timer.py
debis-0.0.1.dist-info/LICENSE
debis-0.0.1.dist-info/METADATA
debis-0.0.1.dist-info/WHEEL
debis-0.0.1.dist-info/top_level.txt
debis-0.0.1.dist-info/RECORD
