Metadata-Version: 2.1
Name: debis
Version: 0.0.1
Summary: Debis web scraping module for notes and student info.
Home-page: UNKNOWN
Author: Ridvan Altun
Author-email: ridvanaltun@outlook.com
License: MIT
Project-URL: Source, https://github.com/ridvanaltun/debis-module/
Keywords: debis
Platform: UNKNOWN
Classifier: License :: OSI Approved :: MIT License
Classifier: Natural Language :: English
Classifier: Development Status :: 5 - Production/Stable
Classifier: Intended Audience :: Developers
Classifier: Topic :: Software Development :: Build Tools
Classifier: Programming Language :: Python :: 3
Classifier: Programming Language :: Python :: 3.3
Classifier: Programming Language :: Python :: 3.4
Classifier: Programming Language :: Python :: 3.5
Classifier: Programming Language :: Python :: 3.6
Classifier: Programming Language :: Python :: 3.7
Requires-Dist: requests
Requires-Dist: bs4
